som_gchu/__init__.py
som_gchu/core.py
som_gchu-0.1.0.dist-info/METADATA
som_gchu-0.1.0.dist-info/WHEEL
som_gchu-0.1.0.dist-info/RECORD
